ogen/__init__.py
ogen/constants.py
ogen/exceptions.py
ogen/ogen.py
ogen/commands/__init__.py
ogen/commands/build.py
ogen/commands/control.py
ogen/commands/create.py
ogen/commands/info.py
ogen/models/__init__.py
ogen/models/project.py
ogen/models/abstract/__init__.py
ogen/models/abstract/base_command.py
ogen/models/abstract/base_config.py
ogen/utils/__init__.py
ogen/utils/docker_compose.py
ogen/utils/docker_file.py
ogen/utils/git.py
ogen/utils/helper.py
ogen-0.1.0.dist-info/entry_points.txt
ogen-0.1.0.dist-info/LICENSE
ogen-0.1.0.dist-info/WHEEL
ogen-0.1.0.dist-info/METADATA
ogen-0.1.0.dist-info/RECORD
