Metadata-Version: 2.1
Name: ogen
Version: 0.1.0
Summary: Odoo Project Generator
Author-email: Ciprian Piron <cix@cix.ro>
Requires-Python: >=3.9
Classifier: Programming Language :: Python :: 3
Classifier: License :: OSI Approved :: MIT License
Classifier: Operating System :: OS Independent
Requires-Dist: click==8.1.3
Requires-Dist: configparser==5.3.0
Requires-Dist: PyYAML==6.0
Project-URL: Bug Tracker, https://github.com/cix-code/odoo-gen/issues
Project-URL: Homepage, https://github.com/cix-code/odoo-gen
